viseval/__init__.py
viseval/table.py
viseval/blocks/__init__.py
viseval/blocks/base.py
viseval/blocks/block_factory.py
viseval/blocks/image.py
viseval/blocks/mesh.py
viseval/blocks/text.py
viseval-0.0.2.3.dist-info/METADATA
viseval-0.0.2.3.dist-info/WHEEL
viseval-0.0.2.3.dist-info/top_level.txt
viseval-0.0.2.3.dist-info/RECORD
