Metadata-Version: 2.1
Name: viseval
Version: 0.0.2.3
Summary: Visualization tool for your evaluation folder
Home-page: https://github.com/submagr/viseval
Author: Shubham Agrawal
Author-email: agshubh191@gmail.com
Classifier: Programming Language :: Python :: 3
Classifier: License :: OSI Approved :: MIT License
Classifier: Operating System :: OS Independent
Requires-Dist: dominate
